greedypermutation/__init__.py
greedypermutation/balltree.py
greedypermutation/clarksongreedy.py
greedypermutation/cli.py
greedypermutation/generic_balltree.py
greedypermutation/greedy.py
greedypermutation/greedytree.py
greedypermutation/knnheap.py
greedypermutation/knnsample.py
greedypermutation/maxheap.py
greedypermutation/neighborgraph.py
greedypermutation/numpygreedy.py
greedypermutation/onehopgreedy.py
greedypermutation/point.py
greedypermutation/quadraticgreedy.py
greedypermutation/vizgreedytree.py
greedypermutation/vizpoint.py
greedypermutation/weightedgraph.py
tests/__init__.py
tests/test_balltree.py
tests/test_cli.py
tests/test_greedy.py
tests/test_greedytree.py
tests/test_knnheap.py
tests/test_knnsample.py
tests/test_maxheap.py
tests/test_neighborgraph.py
tests/test_onehopgreedy.py
tests/test_point.py
greedypermutation-0.5.2.dist-info/LICENSE
greedypermutation-0.5.2.dist-info/METADATA
greedypermutation-0.5.2.dist-info/WHEEL
greedypermutation-0.5.2.dist-info/entry_points.txt
greedypermutation-0.5.2.dist-info/top_level.txt
greedypermutation-0.5.2.dist-info/RECORD
